edgebot/__init__.py
edgebot/api.py
edgebot/bot.py
edgebot/context.py
edgebot/keyboard.py
edgebot/utils.py
edgebot-0.1.2.dist-info/METADATA
edgebot-0.1.2.dist-info/WHEEL
edgebot-0.1.2.dist-info/licenses/LICENSE
edgebot-0.1.2.dist-info/RECORD
