Metadata-Version: 2.4
Name: edgebot
Version: 0.1.2
Summary: SDK для создания Telegram ботов на Cloudflare Workers
Project-URL: Homepage, https://donvalerio.com
Author-email: don Valerio <im@donvalerio.com>
License: MIT
License-File: LICENSE
Keywords: bot,cloudflare,edge,telegram,workers
Classifier: Development Status :: 4 - Beta
Classifier: Intended Audience :: Developers
Classifier: License :: OSI Approved :: MIT License
Classifier: Programming Language :: Python :: 3.10
Classifier: Programming Language :: Python :: 3.11
Classifier: Programming Language :: Python :: 3.12
Classifier: Topic :: Software Development :: Libraries :: Python Modules
Requires-Python: >=3.10
Provides-Extra: dev
Requires-Dist: build; extra == 'dev'
Requires-Dist: twine; extra == 'dev'
